aiida_flux_scheduler/__init__.py
aiida_flux_scheduler/flux.py
aiida_flux_scheduler-0.1.0.dist-info/entry_points.txt
aiida_flux_scheduler-0.1.0.dist-info/licenses/LICENSE.txt
aiida_flux_scheduler-0.1.0.dist-info/WHEEL
aiida_flux_scheduler-0.1.0.dist-info/METADATA
aiida_flux_scheduler-0.1.0.dist-info/RECORD
